django_imdb/__init__.py
django_imdb/admin.py
django_imdb/apps.py
django_imdb/export_tsv.py
django_imdb/import_tsv.py
django_imdb/models.py
django_imdb/pocketsearch.py
django_imdb/py.typed
django_imdb/utils.py
django_imdb/management/__init__.py
django_imdb/management/commands/__init__.py
django_imdb/management/commands/export_imdb_tsv.py
django_imdb/management/commands/import_imdb_tsv.py
django_imdb/management/commands/reindex_search.py
django_imdb/migrations/0001_initial.py
django_imdb/migrations/__init__.py
django_imdb-0.3.5.dist-info/licenses/LICENSE
django_imdb-0.3.5.dist-info/METADATA
django_imdb-0.3.5.dist-info/WHEEL
django_imdb-0.3.5.dist-info/top_level.txt
django_imdb-0.3.5.dist-info/RECORD
